couchbase/__init__.py
couchbase/couchbase.py
couchbase/rules.py
insidecouchbase-2.1.0.dist-info/LICENSE
insidecouchbase-2.1.0.dist-info/METADATA
insidecouchbase-2.1.0.dist-info/WHEEL
insidecouchbase-2.1.0.dist-info/top_level.txt
insidecouchbase-2.1.0.dist-info/RECORD
