Metadata-Version: 2.1
Name: insidecouchbase
Version: 2.1.0
Summary: Check and analyze a couchbase cluster in terms of cluster health,bucket,and replication
Home-page: https://github.com/adiosamig/insidecocuhbase
Author: Huseyin Demir
Author-email: huseyin.d3r@gmail.com
Project-URL: Bug Tracker, https://github.com/adiosamig/insidecocuhbase/issues
Classifier: Programming Language :: Python :: 3
Classifier: License :: OSI Approved :: MIT License
Classifier: Operating System :: OS Independent
Requires-Python: >=3.6
License-File: LICENSE
Requires-Dist: requests
Requires-Dist: tabulate
Requires-Dist: pandas
